{
  "_info": {
    "title": "인용 조문 정비",
    "category": "Ⅱ_등록면허세_등록분/지방세법_시행령",
    "source_pages": ["p055.pdf", "p056.pdf"],
    "duration_target": "60초",
    "law_reference": "지방세법 시행령 제42조의2 제4항",
    "effective_date": "2026-01-01",
    "tone": "친근한 대화체",
    "target_audience": "일반인",
    "emphasis": "실질 변경 없음 - 명확화 조치임을 강조",
    "theme": "탐정사무소",
    "characters": ["제제", "치치"]
  },
  "scenes": [
    {
      "scene_id": 1,
      "duration": "5초",
      "type": "intro",
      "visual": "빈티지 탐정사무소 배경. 제제가 돋보기를 들고 법령 서류를 들여다보며 등장",
      "narration": "건설기계 등록할 때 세금 낸다고요? 잠깐, 이거 알고 넘어가세요!",
      "text_overlay": "등록면허세 과세제외 조문 정비",
      "assets": ["jeje_character", "탐정사무소_배경"]
    },
    {
      "scene_id": 2,
      "duration": "15초",
      "type": "before",
      "visual": "치치가 낡은 법령집을 펼치며 헷갈린 표정. 화면에 '건설기계관리법 시행령 제6조제1항에 따른 등록' 텍스트 표시",
      "narration": "원래 건설기계를 등록할 때 「건설기계관리법 시행령」 제6조제1항을 인용해서 등록면허세를 안 내도 된다고 했거든요. 그런데 이 법이 바뀌어버린 거예요!",
      "text_overlay": "기존: 건설기계관리법 시행령 §6①",
      "assets": []
    },
    {
      "scene_id": 3,
      "duration": "20초",
      "type": "after",
      "visual": "제제가 새 법령 서류를 펼쳐 보이며 밝게 설명. 화면에 '건설기계관리법 제5조'로 바뀐 화살표 그래픽. 중요: 빨간 강조 박스로 '실질 변경 없음' 표시",
      "narration": "2026년부터는 「건설기계관리법」 제5조를 인용하는 걸로 바뀌었어요. 건설기계 소유자 주소지나 사용본거지를 변경할 때 내는 거죠. 중요한 건요, 실제로 내는 세금은 달라지는 게 없어요! 그냥 근거 법령 주소가 바뀐 것뿐이에요.",
      "text_overlay": "개정: 건설기계관리법 §5 | 실질 변경 없음!",
      "assets": ["red_warning"]
    },
    {
      "scene_id": 4,
      "duration": "15초",
      "type": "example",
      "visual": "건설기계(굴착기) 그림과 함께 두 가지 상황 비교. 자동차는 자동차관리법 제11조, 건설기계는 건설기계관리법 제5조 병기",
      "narration": "예를 들어볼게요. 자동차 사용본거지를 옮기면 「자동차관리법」 제11조, 건설기계 주소를 옮기면 「건설기계관리법」 제5조에 따른 변경신고 — 둘 다 등록면허세 안 냅니다! 이전과 똑같아요.",
      "text_overlay": "자동차: 자동차관리법 §11 | 건설기계: 건설기계관리법 §5 → 둘 다 과세 제외",
      "assets": []
    },
    {
      "scene_id": 5,
      "duration": "5초",
      "type": "outro",
      "visual": "2026년 1월 1일 달력 페이지와 탐정사무소 간판. 구독 버튼 등장",
      "narration": "2026년 1월 1일부터 적용이에요. 실질 변화는 없으니 걱정 마세요!",
      "text_overlay": "2026.1.1 시행",
      "assets": ["calendar_icon", "subscribe_button"]
    }
  ]
}
