{
  "_info": {
    "source": "20260101 localtax-special law1.pdf",
    "total_pages": 255,
    "page_offset": 8,
    "note": "문서 페이지 + offset = PDF 파일 번호 (p001.pdf 등)"
  },
  "sections": {
    "Ⅰ_2025년_지방세_지출_재설계_현황": {
      "_doc_start": 1,
      "개요": {
        "01_지방세_지출_개관": 1,
        "02_2025년_지방세_지출_운영_방향": 2,
        "03_지방세_지출_재설계_현황": 3,
        "04_지방세특례제한법_주요_특례_신설_확대": 33
      }
    },
    "Ⅱ_지방세특례제한법령_개정_내용": {
      "_doc_start": 39,
      "개정내용": {
        "01_지방세_특례_정의_규정_명확화": 39,
        "02_지방세_감면_조례_총량_예외_규정_정비": 44,
        "03_임업후계자_등에_대한_감면_요건_추가": 48,
        "04_어업_양식업권_감면_세목_축소": 51,
        "05_한국농어촌공사_사업별_감면율_축소_및_정비": 53,
        "06_지방농수산물공사_감면_연장_및_최소납부적용": 58,
        "07_사회복지법인_등에_대한_감면_연장_및_재설계": 61,
        "08_법률구조법인_한국소비자원에_대한_감면_연장": 71,
        "09_공공매입임대주택_감면대상자_확대": 73,
        "10_지방_준공_후_미분양_아파트_감면_연장_및_확대": 76,
        "11_HUG_미분양_안심환매_사업_지방세_감면_신설": 80,
        "12_생애최초_주택_상시_거주_추징요건_완화": 85,
        "13_출산_양육_주택_취득_감면_연장_및_재설계": 92,
        "14_연구개발_지원을_위한_감면_확대_및_연장": 96,
        "15_스프링클러설비_등_설치_숙박시설_감면": 110,
        "16_관광단지_개발사업시행자_감면_연장_및_재설계": 120,
        "17_벤처기업육성촉진지구_내_벤처기업_감면_연장_및_재설계": 126,
        "18_지식산업센터_등_감면_연장_및_재설계": 129,
        "19_국가철도공단에_대한_감면율_축소": 133,
        "20_한국철도공사에_대한_감면_축소": 136,
        "21_수소전기화물자동차에_대한_감면_연장": 138,
        "22_물류단지_등_감면_연장_및_재설계": 140,
        "23_도시개발사업_등_감면_연장": 146,
        "24_기업도시개발구역_내_창업기업_등_재산세_감면기간_설정": 152,
        "25_반환공여구역_등_감면_연장_및_재설계": 156,
        "26_인구감소지역_감면_연장_및_재설계": 165,
        "27_빈집_정비를_위한_감면_신설": 180,
        "28_산업단지_등_감면_연장_및_재설계": 183,
        "29_한국산업단지공단_감면_연장_및_재설계": 197,
        "30_이전공공기관_등_지방이전_감면_연장": 199,
        "31_사권_제한토지_등_감면_정비": 202,
        "32_지방공기업_등_감면_연장_및_재설계": 206,
        "33_마을회_등_감면_연장_및_재설계": 210,
        "34_개인지방소득세_세액공제_조문_정비": 213,
        "35_인구감소지역_주민_고용_시_법인지방소득세_세액공제_신설": 215,
        "36_고배당기업_주식_배당소득_개인지방소득세_과세특례_신설": 220,
        "37_중과세율_적용_배제특례_사후관리_강화": 222,
        "38_신탁재산_감면_적용_특례_신설": 224,
        "39_인구감소지역_감면_적용_특례_신설": 227,
        "40_감면대상_청년농업법인_연령기준_완화": 230,
        "41_기회발전특구_등_감면_대상_공장_범위_재설계": 232
      }
    },
    "Ⅲ_참고자료": {
      "_doc_start": 245,
      "참고": {
        "01_2026년_최소납부세제_적용대상": 245
      }
    }
  }
}
